README.txt
setup.py
docs/HISTORY.txt
pretaweb/__init__.py
pretaweb.healthcheck.egg-info/PKG-INFO
pretaweb.healthcheck.egg-info/SOURCES.txt
pretaweb.healthcheck.egg-info/dependency_links.txt
pretaweb.healthcheck.egg-info/entry_points.txt
pretaweb.healthcheck.egg-info/namespace_packages.txt
pretaweb.healthcheck.egg-info/not-zip-safe
pretaweb.healthcheck.egg-info/requires.txt
pretaweb.healthcheck.egg-info/top_level.txt
pretaweb/healthcheck/HealthCheck.py
pretaweb/healthcheck/__init__.py
pretaweb/healthcheck/configure.zcml