Metadata-Version: 1.0
Name: pretaweb.healthcheck
Version: 1.0
Summary: Load balancer health checker for a Plone/Zope Instance
Home-page: https://github.com/collective/pretaweb.healthcheck
Author: Adam Terrey
Author-email: software@pretaweb.com
License: GPL
Keywords: Zope Plone load-balancing health-check haproxy
Platform: UNKNOWN
Classifier: Programming Language :: Python
